<?xml version="1.0"?>
<rdf:RDF
    xmlns:dbpedia="http://dbpedia.org/property/"
    xmlns:skos="http://www.w3.org/2004/02/skos/core#"
    xmlns:oddlinker="http://data.linkedmdb.org/resource/oddlinker/"
    xmlns:db="http://data.linkedmdb.org/resource/"
    xmlns:movie="http://data.linkedmdb.org/resource/movie/"
    xmlns:rdf="http://www.w3.org/1999/02/22-rdf-syntax-ns#"
    xmlns:map="file:/C:/d2r-server-0.4/mapping.n3#"
    xmlns:foaf="http://xmlns.com/foaf/0.1/"
    xmlns:d2r="http://sites.wiwiss.fu-berlin.de/suhl/bizer/d2r-server/config.rdf#"
    xmlns:owl="http://www.w3.org/2002/07/owl#"
    xmlns:dc="http://purl.org/dc/terms/"
    xmlns:xsd="http://www.w3.org/2001/XMLSchema#"
    xmlns:rdfs="http://www.w3.org/2000/01/rdf-schema#">
  <rdf:Description rdf:about="http://data.linkedmdb.org/resource/film/68393">
    <movie:actor>
      <movie:actor rdf:about="http://data.linkedmdb.org/resource/actor/31152">
        <movie:performance rdf:resource="http://data.linkedmdb.org/resource/performance/50138"/>
        <movie:performance rdf:resource="http://data.linkedmdb.org/resource/performance/95972"/>
        <movie:performance rdf:resource="http://data.linkedmdb.org/resource/performance/107347"/>
        <movie:performance rdf:resource="http://data.linkedmdb.org/resource/performance/190122"/>
        <movie:actor_actorid rdf:datatype="http://www.w3.org/2001/XMLSchema#int"
        >31152</movie:actor_actorid>
        <movie:performance rdf:resource="http://data.linkedmdb.org/resource/performance/198356"/>
        <movie:performance rdf:resource="http://data.linkedmdb.org/resource/performance/102987"/>
        <movie:performance rdf:resource="http://data.linkedmdb.org/resource/performance/198138"/>
        <movie:performance rdf:resource="http://data.linkedmdb.org/resource/performance/66467"/>
        <movie:performance rdf:resource="http://data.linkedmdb.org/resource/performance/169855"/>
        <movie:actor_netflix_id></movie:actor_netflix_id>
        <movie:performance rdf:resource="http://data.linkedmdb.org/resource/performance/133998"/>
        <movie:performance rdf:resource="http://data.linkedmdb.org/resource/performance/72756"/>
        <movie:performance rdf:resource="http://data.linkedmdb.org/resource/performance/65186"/>
        <rdfs:label>Robert Vaughn (Actor)</rdfs:label>
        <movie:performance rdf:resource="http://data.linkedmdb.org/resource/performance/122606"/>
        <movie:performance rdf:resource="http://data.linkedmdb.org/resource/performance/55133"/>
        <movie:performance rdf:resource="http://data.linkedmdb.org/resource/performance/167172"/>
        <movie:performance rdf:resource="http://data.linkedmdb.org/resource/performance/8566"/>
        <movie:performance rdf:resource="http://data.linkedmdb.org/resource/performance/33166"/>
        <foaf:page>
          <rdf:Description rdf:about="http://www.freebase.com/view/guid/9202a8c04000641f800000000017aac0">
            <rdfs:seeAlso rdf:resource="http://data.linkedmdb.org/sparql?query=DESCRIBE+%3Chttp%3A%2F%2Fwww.freebase.com%2Fview%2Fguid%2F9202a8c04000641f800000000017aac0%3E"/>
          </rdf:Description>
        </foaf:page>
        <movie:performance rdf:resource="http://data.linkedmdb.org/resource/performance/5645"/>
        <movie:performance rdf:resource="http://data.linkedmdb.org/resource/performance/90840"/>
        <movie:performance rdf:resource="http://data.linkedmdb.org/resource/performance/127912"/>
        <movie:performance rdf:resource="http://data.linkedmdb.org/resource/performance/92316"/>
        <movie:performance rdf:resource="http://data.linkedmdb.org/resource/performance/87235"/>
        <movie:performance rdf:resource="http://data.linkedmdb.org/resource/performance/82114"/>
        <movie:actor_name>Robert Vaughn</movie:actor_name>
        <movie:performance rdf:resource="http://data.linkedmdb.org/resource/performance/154605"/>
        <movie:performance rdf:resource="http://data.linkedmdb.org/resource/performance/56439"/>
        <movie:performance rdf:resource="http://data.linkedmdb.org/resource/performance/191372"/>
        <movie:performance rdf:resource="http://data.linkedmdb.org/resource/performance/54117"/>
        <movie:performance rdf:resource="http://data.linkedmdb.org/resource/performance/127613"/>
        <movie:performance rdf:resource="http://data.linkedmdb.org/resource/performance/129218"/>
        <movie:performance rdf:resource="http://data.linkedmdb.org/resource/performance/174155"/>
        <movie:performance rdf:resource="http://data.linkedmdb.org/resource/performance/68073"/>
        <movie:performance rdf:resource="http://data.linkedmdb.org/resource/performance/92214"/>
        <movie:performance rdf:resource="http://data.linkedmdb.org/resource/performance/119575"/>
        <movie:performance rdf:resource="http://data.linkedmdb.org/resource/performance/161311"/>
        <movie:performance rdf:resource="http://data.linkedmdb.org/resource/performance/43706"/>
        <movie:performance rdf:resource="http://data.linkedmdb.org/resource/performance/132186"/>
        <movie:actor_nytimes_id></movie:actor_nytimes_id>
        <movie:performance rdf:resource="http://data.linkedmdb.org/resource/performance/3649"/>
        <movie:performance rdf:resource="http://data.linkedmdb.org/resource/performance/28220"/>
        <movie:performance rdf:resource="http://data.linkedmdb.org/resource/performance/69752"/>
        <movie:performance rdf:resource="http://data.linkedmdb.org/resource/performance/124580"/>
        <movie:performance rdf:resource="http://data.linkedmdb.org/resource/performance/126071"/>
        <movie:performance rdf:resource="http://data.linkedmdb.org/resource/performance/143387"/>
        <rdf:type>
          <rdf:Description rdf:about="http://xmlns.com/foaf/0.1/Person">
            <rdfs:seeAlso rdf:resource="http://data.linkedmdb.org/sparql?query=DESCRIBE+%3Chttp%3A%2F%2Fxmlns.com%2Ffoaf%2F0.1%2FPerson%3E"/>
          </rdf:Description>
        </rdf:type>
        <movie:performance rdf:resource="http://data.linkedmdb.org/resource/performance/149421"/>
      </movie:actor>
    </movie:actor>
  </rdf:Description>
  <rdf:Description rdf:about="http://data.linkedmdb.org/resource/film/19350">
    <movie:actor rdf:resource="http://data.linkedmdb.org/resource/actor/31152"/>
  </rdf:Description>
  <rdf:Description rdf:about="http://data.linkedmdb.org/resource/film/98388">
    <movie:actor rdf:resource="http://data.linkedmdb.org/resource/actor/31152"/>
  </rdf:Description>
  <rdf:Description rdf:about="http://data.linkedmdb.org/resource/film/45951">
    <movie:actor rdf:resource="http://data.linkedmdb.org/resource/actor/31152"/>
  </rdf:Description>
  <rdf:Description rdf:about="http://data.linkedmdb.org/resource/film/63320">
    <movie:actor rdf:resource="http://data.linkedmdb.org/resource/actor/31152"/>
  </rdf:Description>
  <rdf:Description rdf:about="http://data.linkedmdb.org/resource/film/40623">
    <movie:actor rdf:resource="http://data.linkedmdb.org/resource/actor/31152"/>
  </rdf:Description>
  <rdf:Description rdf:about="http://data.linkedmdb.org/resource/film/80850">
    <movie:actor rdf:resource="http://data.linkedmdb.org/resource/actor/31152"/>
  </rdf:Description>
  <rdf:Description rdf:about="http://data.linkedmdb.org/resource/film/59558">
    <movie:actor rdf:resource="http://data.linkedmdb.org/resource/actor/31152"/>
  </rdf:Description>
  <rdf:Description rdf:about="http://data.linkedmdb.org/resource/film/64189">
    <movie:actor rdf:resource="http://data.linkedmdb.org/resource/actor/31152"/>
  </rdf:Description>
  <rdf:Description rdf:about="http://data.linkedmdb.org/resource/film/9023">
    <movie:actor rdf:resource="http://data.linkedmdb.org/resource/actor/31152"/>
  </rdf:Description>
  <rdf:Description rdf:about="http://data.linkedmdb.org/resource/film/60955">
    <movie:actor rdf:resource="http://data.linkedmdb.org/resource/actor/31152"/>
  </rdf:Description>
  <rdf:Description rdf:about="http://data.linkedmdb.org/resource/film/4851">
    <movie:actor rdf:resource="http://data.linkedmdb.org/resource/actor/31152"/>
  </rdf:Description>
  <rdf:Description rdf:about="http://data.linkedmdb.org/resource/film/87500">
    <movie:actor rdf:resource="http://data.linkedmdb.org/resource/actor/31152"/>
  </rdf:Description>
  <rdf:Description rdf:about="http://data.linkedmdb.org/resource/film/98210">
    <movie:actor rdf:resource="http://data.linkedmdb.org/resource/actor/31152"/>
  </rdf:Description>
  <rdf:Description rdf:about="http://data.linkedmdb.org/resource/film/22332">
    <movie:actor rdf:resource="http://data.linkedmdb.org/resource/actor/31152"/>
  </rdf:Description>
  <rdf:Description rdf:about="http://data.linkedmdb.org/resource/film/18386">
    <movie:actor rdf:resource="http://data.linkedmdb.org/resource/actor/31152"/>
  </rdf:Description>
  <rdf:Description rdf:about="http://data.linkedmdb.org/resource/film/56583">
    <movie:actor rdf:resource="http://data.linkedmdb.org/resource/actor/31152"/>
  </rdf:Description>
  <rdf:Description rdf:about="http://data.linkedmdb.org/resource/film/40433">
    <movie:actor rdf:resource="http://data.linkedmdb.org/resource/actor/31152"/>
  </rdf:Description>
  <rdf:Description rdf:about="http://data.linkedmdb.org/resource/film/84124">
    <movie:actor rdf:resource="http://data.linkedmdb.org/resource/actor/31152"/>
  </rdf:Description>
  <rdf:Description rdf:about="http://data.linkedmdb.org/resource/film/41587">
    <movie:actor rdf:resource="http://data.linkedmdb.org/resource/actor/31152"/>
  </rdf:Description>
  <rdf:Description rdf:about="http://data.linkedmdb.org/data/actor/31152">
    <rdfs:comment>Contents of this file may include content from 
		      FreeBase (http://www.freebase.com) or Wikipedia 
		      (http://www.wikipedia.org) licensed under CC-BY
		      (http://www.freebase.com/view/common/license/cc_attribution_25)
		      or GFDL (http://en.wikipedia.org/wiki/Wikipedia:Text_of_the_GNU_Free_Documentation_License). 
		      Refer to http://www.linkedmdb.org:8080/Main/Licensing for more details.</rdfs:comment>
    <rdfs:label>RDF Description of Robert Vaughn (Actor)</rdfs:label>
    <foaf:primaryTopic rdf:resource="http://data.linkedmdb.org/resource/actor/31152"/>
  </rdf:Description>
  <rdf:Description rdf:about="http://data.linkedmdb.org/resource/film/73421">
    <movie:actor rdf:resource="http://data.linkedmdb.org/resource/actor/31152"/>
  </rdf:Description>
  <rdf:Description rdf:about="http://data.linkedmdb.org/resource/film/38165">
    <movie:actor rdf:resource="http://data.linkedmdb.org/resource/actor/31152"/>
  </rdf:Description>
  <rdf:Description rdf:about="http://data.linkedmdb.org/resource/film/46889">
    <movie:actor rdf:resource="http://data.linkedmdb.org/resource/actor/31152"/>
  </rdf:Description>
  <rdf:Description rdf:about="http://data.linkedmdb.org/resource/film/40755">
    <movie:actor rdf:resource="http://data.linkedmdb.org/resource/actor/31152"/>
  </rdf:Description>
  <rdf:Description rdf:about="http://data.linkedmdb.org/resource/film/2728">
    <movie:actor rdf:resource="http://data.linkedmdb.org/resource/actor/31152"/>
  </rdf:Description>
  <rdf:Description rdf:about="http://data.linkedmdb.org/resource/film/55203">
    <movie:actor rdf:resource="http://data.linkedmdb.org/resource/actor/31152"/>
  </rdf:Description>
  <rdf:Description rdf:about="http://data.linkedmdb.org/resource/film/225">
    <movie:actor rdf:resource="http://data.linkedmdb.org/resource/actor/31152"/>
  </rdf:Description>
  <rdf:Description rdf:about="http://data.linkedmdb.org/resource/film/998">
    <movie:actor rdf:resource="http://data.linkedmdb.org/resource/actor/31152"/>
  </rdf:Description>
  <rdf:Description rdf:about="http://data.linkedmdb.org/resource/film/40036">
    <movie:actor rdf:resource="http://data.linkedmdb.org/resource/actor/31152"/>
  </rdf:Description>
  <rdf:Description rdf:about="http://data.linkedmdb.org/resource/film/48724">
    <movie:actor rdf:resource="http://data.linkedmdb.org/resource/actor/31152"/>
  </rdf:Description>
  <rdf:Description rdf:about="http://data.linkedmdb.org/resource/film/6206">
    <movie:actor rdf:resource="http://data.linkedmdb.org/resource/actor/31152"/>
  </rdf:Description>
  <rdf:Description rdf:about="http://data.linkedmdb.org/resource/film/39394">
    <movie:actor rdf:resource="http://data.linkedmdb.org/resource/actor/31152"/>
  </rdf:Description>
  <rdf:Description rdf:about="http://data.linkedmdb.org/resource/film/38547">
    <movie:actor rdf:resource="http://data.linkedmdb.org/resource/actor/31152"/>
  </rdf:Description>
  <rdf:Description rdf:about="http://data.linkedmdb.org/resource/film/17085">
    <movie:actor rdf:resource="http://data.linkedmdb.org/resource/actor/31152"/>
  </rdf:Description>
  <rdf:Description rdf:about="http://data.linkedmdb.org/resource/film/62015">
    <movie:actor rdf:resource="http://data.linkedmdb.org/resource/actor/31152"/>
  </rdf:Description>
  <rdf:Description rdf:about="http://data.linkedmdb.org/resource/film/53133">
    <movie:actor rdf:resource="http://data.linkedmdb.org/resource/actor/31152"/>
  </rdf:Description>
  <rdf:Description rdf:about="http://data.linkedmdb.org/resource/film/19420">
    <movie:actor rdf:resource="http://data.linkedmdb.org/resource/actor/31152"/>
  </rdf:Description>
  <rdf:Description rdf:about="http://data.linkedmdb.org/resource/film/16636">
    <movie:actor rdf:resource="http://data.linkedmdb.org/resource/actor/31152"/>
  </rdf:Description>
  <rdf:Description rdf:about="http://data.linkedmdb.org/resource/film/40875">
    <movie:actor rdf:resource="http://data.linkedmdb.org/resource/actor/31152"/>
  </rdf:Description>
  <rdf:Description rdf:about="http://data.linkedmdb.org/resource/film/5511">
    <movie:actor rdf:resource="http://data.linkedmdb.org/resource/actor/31152"/>
  </rdf:Description>
  <rdf:Description rdf:about="http://data.linkedmdb.org/resource/film/78542">
    <movie:actor rdf:resource="http://data.linkedmdb.org/resource/actor/31152"/>
  </rdf:Description>
  <rdf:Description rdf:about="http://data.linkedmdb.org/resource/film/63104">
    <movie:actor rdf:resource="http://data.linkedmdb.org/resource/actor/31152"/>
  </rdf:Description>
  <rdf:Description rdf:about="http://data.linkedmdb.org/resource/film/48528">
    <movie:actor rdf:resource="http://data.linkedmdb.org/resource/actor/31152"/>
  </rdf:Description>
</rdf:RDF>
