<?xml version="1.0"?>
<rdf:RDF
    xmlns:dbpedia="http://dbpedia.org/property/"
    xmlns:skos="http://www.w3.org/2004/02/skos/core#"
    xmlns:oddlinker="http://data.linkedmdb.org/resource/oddlinker/"
    xmlns:db="http://data.linkedmdb.org/resource/"
    xmlns:movie="http://data.linkedmdb.org/resource/movie/"
    xmlns:rdf="http://www.w3.org/1999/02/22-rdf-syntax-ns#"
    xmlns:map="file:/C:/d2r-server-0.4/mapping.n3#"
    xmlns:foaf="http://xmlns.com/foaf/0.1/"
    xmlns:d2r="http://sites.wiwiss.fu-berlin.de/suhl/bizer/d2r-server/config.rdf#"
    xmlns:owl="http://www.w3.org/2002/07/owl#"
    xmlns:dc="http://purl.org/dc/terms/"
    xmlns:xsd="http://www.w3.org/2001/XMLSchema#"
    xmlns:rdfs="http://www.w3.org/2000/01/rdf-schema#">
  <rdf:Description rdf:about="http://data.linkedmdb.org/resource/interlink/135730">
    <oddlinker:link_source>
      <movie:film rdf:about="http://data.linkedmdb.org/resource/film/1949">
        <movie:actor rdf:resource="http://data.linkedmdb.org/resource/actor/44104"/>
        <movie:rating rdf:resource="http://data.linkedmdb.org/resource/content_rating/3"/>
        <dc:title>Primer</dc:title>
        <movie:actor rdf:resource="http://data.linkedmdb.org/resource/actor/5986"/>
        <movie:performance rdf:resource="http://data.linkedmdb.org/resource/performance/23421"/>
        <movie:runtime>79</movie:runtime>
        <movie:film_subject rdf:resource="http://data.linkedmdb.org/resource/film_subject/444"/>
        <movie:genre rdf:resource="http://data.linkedmdb.org/resource/film_genre/23"/>
        <skos:subject rdf:resource="http://data.linkedmdb.org/resource/film_subject/444"/>
        <foaf:page>
          <rdf:Description rdf:about="http://www.rottentomatoes.com/alias?type=imdbid&amp;s=0390384">
            <rdfs:seeAlso rdf:resource="http://data.linkedmdb.org/sparql?query=DESCRIBE+%3Chttp%3A%2F%2Fwww.rottentomatoes.com%2Falias%3Ftype%3Dimdbid%26s%3D0390384%3E"/>
          </rdf:Description>
        </foaf:page>
        <movie:editor rdf:resource="http://data.linkedmdb.org/resource/editor/2659"/>
        <movie:initial_release_date>2004-10-08</movie:initial_release_date>
        <movie:filmid rdf:datatype="http://www.w3.org/2001/XMLSchema#int"
        >1949</movie:filmid>
        <movie:director>
          <rdf:Description rdf:about="http://data.linkedmdb.org/resource/director/11947">
            <foaf:made rdf:resource="http://data.linkedmdb.org/resource/film/1949"/>
          </rdf:Description>
        </movie:director>
        <movie:genre rdf:resource="http://data.linkedmdb.org/resource/film_genre/4"/>
        <movie:film_cut rdf:resource="http://data.linkedmdb.org/resource/film_cut/4991"/>
        <movie:producer rdf:resource="http://data.linkedmdb.org/resource/producer/12297"/>
        <movie:writer rdf:resource="http://data.linkedmdb.org/resource/writer/17901"/>
        <rdfs:label>Primer</rdfs:label>
        <foaf:page>
          <rdf:Description rdf:about="http://www.freebase.com/view/guid/9202a8c04000641f8000000000449b29">
            <rdfs:seeAlso rdf:resource="http://data.linkedmdb.org/sparql?query=DESCRIBE+%3Chttp%3A%2F%2Fwww.freebase.com%2Fview%2Fguid%2F9202a8c04000641f8000000000449b29%3E"/>
          </rdf:Description>
        </foaf:page>
        <foaf:page>
          <rdf:Description rdf:about="http://www.imdb.com/title/tt0390384">
            <rdfs:seeAlso rdf:resource="http://data.linkedmdb.org/sparql?query=DESCRIBE+%3Chttp%3A%2F%2Fwww.imdb.com%2Ftitle%2Ftt0390384%3E"/>
          </rdf:Description>
        </foaf:page>
        <movie:music_contributor rdf:resource="http://data.linkedmdb.org/resource/music_contributor/5476"/>
        <movie:language>
          <rdf:Description rdf:about="http://www.lingvoj.org/lingvo/en">
            <rdfs:seeAlso rdf:resource="http://data.linkedmdb.org/sparql?query=DESCRIBE+%3Chttp%3A%2F%2Fwww.lingvoj.org%2Flingvo%2Fen%3E"/>
          </rdf:Description>
        </movie:language>
        <dc:date>2004-10-08</dc:date>
        <movie:performance rdf:resource="http://data.linkedmdb.org/resource/performance/23420"/>
        <movie:film_series rdf:resource="http://data.linkedmdb.org/resource/film_series/50"/>
      </movie:film>
    </oddlinker:link_source>
  </rdf:Description>
  <rdf:Description rdf:about="http://data.linkedmdb.org/data/film/1949">
    <rdfs:comment>Contents of this file may include content from 
		      FreeBase (http://www.freebase.com) or Wikipedia 
		      (http://www.wikipedia.org) licensed under CC-BY
		      (http://www.freebase.com/view/common/license/cc_attribution_25)
		      or GFDL (http://en.wikipedia.org/wiki/Wikipedia:Text_of_the_GNU_Free_Documentation_License). 
		      Refer to http://www.linkedmdb.org:8080/Main/Licensing for more details.</rdfs:comment>
    <rdfs:label>RDF Description of Primer</rdfs:label>
    <foaf:primaryTopic rdf:resource="http://data.linkedmdb.org/resource/film/1949"/>
  </rdf:Description>
</rdf:RDF>
